YokAPI/__init__.py
YokAPI/models/__init__.py
YokAPI/models/data_model.py
YokAPI/scraper/__init__.py
YokAPI/scraper/fetcher.py
YokAPI/scraper/parser.py
YokAPI/scraper/programs.py
YokAPI/scraper/selectors.py
yokapi-1.1.7.dist-info/licenses/LICENSE
yokapi-1.1.7.dist-info/METADATA
yokapi-1.1.7.dist-info/WHEEL
yokapi-1.1.7.dist-info/top_level.txt
yokapi-1.1.7.dist-info/RECORD
