Metadata-Version: 2.4
Name: YokAPI
Version: 1.1.7
Summary: Unofficial  API for YokAtlas
Home-page: https://github.com/izcir/YokAPI
Author: IZCI
Author-email: ramazan.izcir@gmail.com
License: MIT
Classifier: Programming Language :: Python :: 3
Classifier: License :: OSI Approved :: MIT License
Classifier: Operating System :: OS Independent
Requires-Python: >=3.10
License-File: LICENSE
Requires-Dist: aiohttp==3.12.15
Requires-Dist: certifi==2025.8.3
Requires-Dist: bs4==0.0.2
Requires-Dist: pydantic==2.10.6
Requires-Dist: pandas==2.2.3
Dynamic: author
Dynamic: author-email
Dynamic: classifier
Dynamic: description
Dynamic: description-content-type
Dynamic: home-page
Dynamic: license
Dynamic: license-file
Dynamic: requires-dist
Dynamic: requires-python
Dynamic: summary
